darkencryption/__init__.py
darkencryption/darkencryption.py
darkencryption-0.0.2.dist-info/LICENSE
darkencryption-0.0.2.dist-info/METADATA
darkencryption-0.0.2.dist-info/WHEEL
darkencryption-0.0.2.dist-info/top_level.txt
darkencryption-0.0.2.dist-info/RECORD
