Metadata-Version: 2.1
Name: darkencryption
Version: 0.0.2
Summary: A package to encrypt data
Author-email: Dark_Eden <darkedenc9@gmail.com>
Project-URL: Homepage, https://github.com/DarkEden-coding/darkencryption
Project-URL: Bug Tracker, https://github.com/DarkEden-coding/darkencryption/issues
Classifier: Programming Language :: Python :: 3
Classifier: License :: OSI Approved :: MIT License
Classifier: Operating System :: OS Independent
Requires-Python: >=3.7
License-File: LICENSE
